LogisticScoreCard/LogisticScoreCard.py
LogisticScoreCard/__init__.py
ScoreModel-1.0.0.dist-info/DESCRIPTION.rst
ScoreModel-1.0.0.dist-info/METADATA
ScoreModel-1.0.0.dist-info/RECORD
ScoreModel-1.0.0.dist-info/WHEEL
ScoreModel-1.0.0.dist-info/metadata.json
ScoreModel-1.0.0.dist-info/top_level.txt
